main.py
gyy_mcp-1.1.2.dist-info/METADATA
gyy_mcp-1.1.2.dist-info/WHEEL
gyy_mcp-1.1.2.dist-info/entry_points.txt
gyy_mcp-1.1.2.dist-info/top_level.txt
gyy_mcp-1.1.2.dist-info/RECORD
