Metadata-Version: 2.4
Name: gyy-mcp
Version: 1.1.2
Summary: A FastMCP-based MCP tool with image recognition using Ollama qwen3-vl:8b model
Author-email: Your Name <your.email@example.com>
License: MIT
Project-URL: Repository, https://github.com/yourusername/gyy-mcp.git
Keywords: mcp,fastmcp,tool,ai,claude
Classifier: Development Status :: 4 - Beta
Classifier: Intended Audience :: Developers
Classifier: License :: OSI Approved :: MIT License
Classifier: Programming Language :: Python :: 3
Classifier: Programming Language :: Python :: 3.8
Classifier: Programming Language :: Python :: 3.9
Classifier: Programming Language :: Python :: 3.10
Classifier: Programming Language :: Python :: 3.11
Classifier: Programming Language :: Python :: 3.12
Classifier: Programming Language :: Python :: 3.13
Requires-Python: >=3.8
Requires-Dist: fastmcp==2.14.2
Requires-Dist: requests>=2.31.0
Requires-Dist: Pillow>=10.0.0
